{"status_cd":0,"error_cd":0,"data":{"replace":[{"t_member_id":"783098","t_member_cards":[{"id":"1921443","m_card_id":"6013012","rare":"6","attribute":"2","lv":"128","lv_max":"136","exp":"3788138","exp_evo":"0","limit_break_num":"8","created":"2018-03-03 16:28:02","modified":"2018-04-07 15:08:25","acommands":["7","7","1"],"pcommands":["5","1","1"],"price":45},{"id":"2126271","m_card_id":"4005015","rare":"3","attribute":"5","lv":"42","lv_max":"60","exp":"22839","exp_evo":"34","limit_break_num":"1","created":"2018-03-07 00:01:34","modified":"2018-04-07 15:08:25","acommands":["1","1","1"],"pcommands":["1","1","1"],"price":10},{"id":"1382465","m_card_id":"4002015","rare":"3","attribute":"5","lv":"42","lv_max":"60","exp":"22839","exp_evo":"34","limit_break_num":"1","created":"2018-02-25 21:34:34","modified":"2018-04-07 15:08:25","acommands":["1","1","1"],"pcommands":["1","1","1"],"price":10},{"id":"2695840","m_card_id":"6010012","rare":"2","attribute":"2","lv":"40","lv_max":"40","exp":"17991","exp_evo":"238","limit_break_num":"0","created":"2018-04-06 17:19:59","modified":"2018-04-07 15:08:25","acommands":["1","1","1"],"pcommands":["1","1","1"],"price":5},{"id":"2690390","m_card_id":"4003011","rare":"2","attribute":"1","lv":"40","lv_max":"40","exp":"17991","exp_evo":"238","limit_break_num":"1","created":"2018-04-06 16:05:26","modified":"2018-04-07 15:08:25","acommands":["1","1","1"],"pcommands":["1","1","1"],"price":10}],"t_member_eqs":[{"id":"7911157","m_eq_id":"10257","eq_category":"1","eq_type":"2","eq_kind":"5","rare":"7","rank":"1","enh_num":"12","t_member_card_id":"1921443","pop":"1","lock_flg":"1","position":"1","enchant_type_base":"0","created":"2018-04-07 08:11:38","modified":"2018-04-07 11:08:42","enchant_types":["3","7","3","6"],"enchant_values":["75","7","70","7"],"price":192400,"enh_mana":15000,"enh_rate":5},{"id":"3498191","m_eq_id":"21214","eq_category":"2","eq_type":"12","eq_kind":"1","rare":"4","rank":"1","enh_num":"15","t_member_card_id":"1921443","pop":"0","lock_flg":"1","position":"2","enchant_type_base":"0","created":"2018-02-26 23:52:40","modified":"2018-04-07 11:08:42","enchant_types":["2","6","10","7"],"enchant_values":["4","4","1","3"],"price":98000,"enh_mana":0,"enh_rate":0},{"id":"6402648","m_eq_id":"31816","eq_category":"3","eq_type":"18","eq_kind":"1","rare":"6","rank":"2","enh_num":"12","t_member_card_id":"1921443","pop":"0","lock_flg":"1","position":"3","enchant_type_base":"0","created":"2018-03-19 14:24:15","modified":"2018-04-07 11:08:42","enchant_types":["4","9","4","3"],"enchant_values":["6","7","5","80"],"price":91700,"enh_mana":8000,"enh_rate":10},{"id":"5767742","m_eq_id":"45616","eq_category":"4","eq_type":"56","eq_kind":"1","rare":"6","rank":"1","enh_num":"15","t_member_card_id":"1921443","pop":"0","lock_flg":"0","position":"4","enchant_type_base":"7","created":"2018-03-13 21:07:56","modified":"2018-04-07 11:08:42","enchant_types":["5","8","4","4"],"enchant_values":["75","4","6","6"],"price":228750,"enh_mana":0,"enh_rate":0},{"id":"6703308","m_eq_id":"45616","eq_category":"4","eq_type":"56","eq_kind":"1","rare":"6","rank":"1","enh_num":"14","t_member_card_id":"1921443","pop":"0","lock_flg":"0","position":"5","enchant_type_base":"8","created":"2018-03-22 13:35:42","modified":"2018-04-07 11:08:42","enchant_types":["3","9","4","7"],"enchant_values":["75","5","5","4"],"price":168750,"enh_mana":9000,"enh_rate":5},{"id":"5717672","m_eq_id":"45616","eq_category":"4","eq_type":"56","eq_kind":"1","rare":"6","rank":"1","enh_num":"15","t_member_card_id":"1921443","pop":"0","lock_flg":"0","position":"6","enchant_type_base":"8","created":"2018-03-13 12:31:44","modified":"2018-04-07 11:08:42","enchant_types":["4","9","1","6"],"enchant_values":["5","5","570","5"],"price":228750,"enh_mana":0,"enh_rate":0}],"t_memb
1000
er_formation":{"id":"89273","m_formation_id":"3","lv":"1"},"t_member_event_stages":[{"id":"40353","m_event_id":"3","m_event_dungeon_id":"3","m_event_stage_id":"310","play_speak":"0","is_cleared":"1","daily_cnt":"0","count_date":"2018-02-22 07:04:21"}],"t_member_story":[],"battle":{"t_member_id":783098,"stage_id":310,"category":2,"type":11,"level":11,"deck_no":6,"t_member_formation_id":89273,"battle_id":6296168,"waves":[{"no":1,"turn":50,"clear_type":1,"gimmick_type":0,"gimmick_monster_id":0,"monsters":[{"no":1,"px":"0","py":"1","id":"3100101","ai_id":"6006014","next_ai_id":"0","m_card_id":"6006014","name":"短気プリニーキンカン","scale":"98","is_boss":"0","lv":"125","hp":"10702","atk":"1655","def":"1911","spd":"135","cri_per":"30","cri_damage":50,"luck":"0","flee":"0","point":68,"mana":83,"exp_card":147,"exp_evo":17,"def_status":"0","object_type":"1","m_acommand_lv":["1","1","1","1","1"],"m_pcommand_lv":["1","1","1"],"m_acommand_id":["600640","600641","600642","0","0"],"m_pcommand_id":["113","114","0"],"drops":[],"move":"2"},{"no":1,"px":"2","py":"1","id":"3100102","ai_id":"6006012","next_ai_id":"0","m_card_id":"6006012","name":"冷徹プリニーサンカク","scale":"98","is_boss":"0","lv":"125","hp":"11530","atk":"1520","def":"2062","spd":"135","cri_per":"30","cri_damage":50,"luck":"0","flee":"0","point":54,"mana":71,"exp_card":131,"exp_evo":0,"def_status":"0","object_type":"1","m_acommand_lv":["1","1","1","1","1"],"m_pcommand_lv":["1","1","1"],"m_acommand_id":["600620","600621","600622","0","0"],"m_pcommand_id":["113","114","0"],"drops":[],"move":"2"},{"no":1,"px":"1","py":"2","id":"3100103","ai_id":"6006011","next_ai_id":"0","m_card_id":"6006011","name":"熱血プリニーゲンコツ","scale":"98","is_boss":"0","lv":"125","hp":"10702","atk":"1655","def":"2062","spd":"135","cri_per":"30","cri_damage":50,"luck":"0","flee":"0","point":54,"mana":71,"exp_card":131,"exp_evo":0,"def_status":"0","object_type":"1","m_acommand_lv":["1","1","1","1","1"],"m_pcommand_lv":["1","1","1"],"m_acommand_id":["600610","600611","600612","0","0"],"m_pcommand_id":["113","114","0"],"drops":[],"move":"2"},{"no":1,"px":"0","py":"3","id":"3100104","ai_id":"6006015","next_ai_id":"0","m_card_id":"6006015","name":"慎重プリニーピール","scale":"98","is_boss":"0","lv":"125","hp":"10702","atk":"1655","def":"2062","spd":"146","cri_per":"30","cri_damage":50,"luck":"0","flee":"0","point":54,"mana":71,"exp_card":131,"exp_evo":0,"def_status":"0","object_type":"1","m_acommand_lv":["1","1","1","1","1"],"m_pcommand_lv":["1","1","1"],"m_acommand_id":["600650","600651","600652","0","0"],"m_pcommand_id":["113","114","0"],"drops":[],"move":"2"},{"no":1,"px":"2","py":"3","id":"3100105","ai_id":"6006013","next_ai_id":"0","m_card_id":"6006013","name":"平穏プリニーセセリー","scale":"98","is_boss":"0","lv":"125","hp":"10702","atk":"1520","def":"1911","spd":"146","cri_per":"30","cri_damage":50,"luck":"0","flee":"0","point":54,"mana":71,"exp_card":131,"exp_evo":0,"def_status":"0","object_type":"1","m_acommand_lv":["1","1","1","1","1"],"m_pcommand_lv":["1","1","1"],"m_acommand_id":["600630","600631","600632","0","0"],"m_pcommand_id":["113","114","0"],"drops":[],"move":"2"}],"background_id":2201,"background_effect_id":0,"background_color":"7F7F7F","meta_area":"0"},{"no":2,"turn":50,"clear_type":1,"gimmick_type":0,"gimmick_monster_id":0,"monsters":[{"no":2,"px":"0","py":"0","id":"3100201","ai_id":"6006015","next_ai_id":"0","m_card_id":"6006015","name":"慎重プリニーピール","scale":"98","is_boss":"0","lv":"125","hp":"10702","atk":"1655","def":"2062","spd":"146","cri_per":"30","cri_damage":50,"luck":"0","flee":"0","point":54,"mana":71,"exp_card":131,"exp_evo":0,"def_status":"0","object_type":"1","m_acommand_lv":["1","1","1","1","1"],"m_pcommand_lv":["1","1","1"],"m_acommand_id":["600650","600651","600652","0","0"],"m_pcommand_id":["113","114","0"],"drops":[],"move":"2"},{"no":2,"px":"2","py":"0","id":"3100202","ai_id":"6006013","next_ai_id":"0","m_card_id":"6006013","name":"平穏プリニーセセリー","scale":"98","is_boss":"0","lv":
1000
"125","hp":"10702","atk":"1520","def":"1911","spd":"146","cri_per":"30","cri_damage":50,"luck":"0","flee":"0","point":54,"mana":71,"exp_card":131,"exp_evo":0,"def_status":"0","object_type":"1","m_acommand_lv":["1","1","1","1","1"],"m_pcommand_lv":["1","1","1"],"m_acommand_id":["600630","600631","600632","0","0"],"m_pcommand_id":["113","114","0"],"drops":[],"move":"2"},{"no":2,"px":"0","py":"2","id":"3100203","ai_id":"6006011","next_ai_id":"0","m_card_id":"6006011","name":"熱血プリニーゲンコツ","scale":"98","is_boss":"0","lv":"125","hp":"10702","atk":"1655","def":"2062","spd":"135","cri_per":"30","cri_damage":50,"luck":"0","flee":"0","point":54,"mana":71,"exp_card":131,"exp_evo":0,"def_status":"0","object_type":"1","m_acommand_lv":["1","1","1","1","1"],"m_pcommand_lv":["1","1","1"],"m_acommand_id":["600610","600611","600612","0","0"],"m_pcommand_id":["113","114","0"],"drops":[],"move":"2"},{"no":2,"px":"0","py":"4","id":"3100204","ai_id":"6006014","next_ai_id":"0","m_card_id":"6006014","name":"短気プリニーキンカン","scale":"98","is_boss":"0","lv":"125","hp":"10702","atk":"1655","def":"1911","spd":"135","cri_per":"30","cri_damage":50,"luck":"0","flee":"0","point":54,"mana":71,"exp_card":131,"exp_evo":0,"def_status":"0","object_type":"1","m_acommand_lv":["1","1","1","1","1"],"m_pcommand_lv":["1","1","1"],"m_acommand_id":["600640","600641","600642","0","0"],"m_pcommand_id":["113","114","0"],"drops":[],"move":"2"},{"no":2,"px":"2","py":"4","id":"3100205","ai_id":"6006012","next_ai_id":"0","m_card_id":"6006012","name":"冷徹プリニーサンカク","scale":"98","is_boss":"0","lv":"125","hp":"11530","atk":"1520","def":"2062","spd":"135","cri_per":"30","cri_damage":50,"luck":"0","flee":"0","point":54,"mana":71,"exp_card":131,"exp_evo":0,"def_status":"0","object_type":"1","m_acommand_lv":["1","1","1","1","1"],"m_pcommand_lv":["1","1","1"],"m_acommand_id":["600620","600621","600622","0","0"],"m_pcommand_id":["113","114","0"],"drops":[],"move":"2"}],"background_id":2201,"background_effect_id":0,"background_color":"7F7F7F","meta_area":"0"},{"no":3,"turn":50,"clear_type":1,"gimmick_type":0,"gimmick_monster_id":0,"monsters":[{"no":3,"px":"0","py":"0","id":"3100301","ai_id":"6006014","next_ai_id":"0","m_card_id":"6006014","name":"短気プリニーキンカン","scale":"98","is_boss":"0","lv":"125","hp":"10702","atk":"1655","def":"1911","spd":"135","cri_per":"30","cri_damage":50,"luck":"0","flee":"0","point":54,"mana":71,"exp_card":131,"exp_evo":0,"def_status":"0","object_type":"1","m_acommand_lv":["1","1","1","1","1"],"m_pcommand_lv":["1","1","1"],"m_acommand_id":["600640","600641","600642","0","0"],"m_pcommand_id":["113","114","0"],"drops":[],"move":"2"},{"no":3,"px":"2","py":"0","id":"3100302","ai_id":"6006012","next_ai_id":"0","m_card_id":"6006012","name":"冷徹プリニーサンカク","scale":"98","is_boss":"0","lv":"125","hp":"11530","atk":"1520","def":"2062","spd":"135","cri_per":"30","cri_damage":50,"luck":"0","flee":"0","point":54,"mana":71,"exp_card":131,"exp_evo":0,"def_status":"0","object_type":"1","m_acommand_lv":["1","1","1","1","1"],"m_pcommand_lv":["1","1","1"],"m_acommand_id":["600620","600621","600622","0","0"],"m_pcommand_id":["113","114","0"],"drops":[],"move":"2"},{"no":3,"px":"1","py":"2","id":"3100303","ai_id":"6006011","next_ai_id":"0","m_card_id":"6006011","name":"熱血プリニーゲンコツ","scale":"98","is_boss":"0","lv":"125","hp":"10702","atk":"1655","def":"2062","spd":"135","cri_per":"30","cri_damage":50,"luck":"0","flee":"0","point":54,"mana":71,"exp_card":131,"exp_evo":0,"def_status":"0","object_type":"1","m_acommand_lv":["1","1","1","1","1"],"m_pcommand_lv":["1","1","1"],"m_acommand_id":["600610","600611","600612","0","0"],"m_pcommand_id":["113","114","0"],"drops":[],"move":"2"},{"no":3,"px":"0","py":"4","id":"3100304","ai_id":"6006015","next_ai_id":"0","m_card_id":"6006015","name":"慎重プリニーピール","scale":"98","is_boss":"0","lv":"125","hp":"10702","atk":"1655","def":"2062","spd":"146","cri_per":"30","cri_damage":50,"luck":"0","flee":"0","point":54,"mana":71,"exp
1000
_card":131,"exp_evo":0,"def_status":"0","object_type":"1","m_acommand_lv":["1","1","1","1","1"],"m_pcommand_lv":["1","1","1"],"m_acommand_id":["600650","600651","600652","0","0"],"m_pcommand_id":["113","114","0"],"drops":[],"move":"2"},{"no":3,"px":"2","py":"4","id":"3100305","ai_id":"6006013","next_ai_id":"0","m_card_id":"6006013","name":"平穏プリニーセセリー","scale":"98","is_boss":"0","lv":"125","hp":"10702","atk":"1520","def":"1911","spd":"146","cri_per":"30","cri_damage":50,"luck":"0","flee":"0","point":54,"mana":71,"exp_card":131,"exp_evo":0,"def_status":"0","object_type":"1","m_acommand_lv":["1","1","1","1","1"],"m_pcommand_lv":["1","1","1"],"m_acommand_id":["600630","600631","600632","0","0"],"m_pcommand_id":["113","114","0"],"drops":[],"move":"2"}],"background_id":2201,"background_effect_id":0,"background_color":"7F7F7F","meta_area":"0"},{"no":4,"turn":50,"clear_type":1,"gimmick_type":0,"gimmick_monster_id":0,"monsters":[{"no":4,"px":"0","py":"0","id":"3100401","ai_id":"6006011","next_ai_id":"0","m_card_id":"6006011","name":"熱血プリニーゲンコツ","scale":"98","is_boss":"0","lv":"125","hp":"10702","atk":"1655","def":"2062","spd":"135","cri_per":"30","cri_damage":50,"luck":"0","flee":"0","point":54,"mana":71,"exp_card":131,"exp_evo":0,"def_status":"0","object_type":"1","m_acommand_lv":["1","1","1","1","1"],"m_pcommand_lv":["1","1","1"],"m_acommand_id":["600610","600611","600612","0","0"],"m_pcommand_id":["113","114","0"],"drops":[],"move":"2"},{"no":4,"px":"1","py":"1","id":"3100402","ai_id":"6006011","next_ai_id":"0","m_card_id":"6006011","name":"熱血プリニーゲンコツ","scale":"98","is_boss":"0","lv":"125","hp":"10702","atk":"1655","def":"2062","spd":"135","cri_per":"30","cri_damage":50,"luck":"0","flee":"0","point":54,"mana":71,"exp_card":131,"exp_evo":0,"def_status":"0","object_type":"1","m_acommand_lv":["1","1","1","1","1"],"m_pcommand_lv":["1","1","1"],"m_acommand_id":["600610","600611","600612","0","0"],"m_pcommand_id":["113","114","0"],"drops":[],"move":"2"},{"no":4,"px":"0","py":"2","id":"3100403","ai_id":"113","next_ai_id":"113","m_card_id":"6008012","name":"傍若無人 エリンギャー親分","scale":"150","is_boss":"1","lv":"135","hp":"30369","atk":"2154","def":"2266","spd":"157","cri_per":"30","cri_damage":50,"luck":"0","flee":"0","point":1041,"mana":1362,"exp_card":2505,"exp_evo":17,"def_status":"10&999#11&999#12&999#15&999#16&999#17&999#19&999","object_type":"1","m_acommand_lv":["1","1","1","1","1"],"m_pcommand_lv":["1","1","1"],"m_acommand_id":["600823","600824","600825","0","0"],"m_pcommand_id":["152","153","0"],"drops":[],"move":"2"},{"no":4,"px":"1","py":"3","id":"3100404","ai_id":"6006011","next_ai_id":"0","m_card_id":"6006011","name":"熱血プリニーゲンコツ","scale":"98","is_boss":"0","lv":"125","hp":"10702","atk":"1655","def":"2062","spd":"135","cri_per":"30","cri_damage":50,"luck":"0","flee":"0","point":54,"mana":71,"exp_card":131,"exp_evo":0,"def_status":"0","object_type":"1","m_acommand_lv":["1","1","1","1","1"],"m_pcommand_lv":["1","1","1"],"m_acommand_id":["600610","600611","600612","0","0"],"m_pcommand_id":["113","114","0"],"drops":[],"move":"2"},{"no":4,"px":"0","py":"4","id":"3100405","ai_id":"6006011","next_ai_id":"0","m_card_id":"6006011","name":"熱血プリニーゲンコツ","scale":"98","is_boss":"0","lv":"125","hp":"10702","atk":"1655","def":"2062","spd":"135","cri_per":"30","cri_damage":50,"luck":"0","flee":"0","point":54,"mana":71,"exp_card":131,"exp_evo":0,"def_status":"0","object_type":"1","m_acommand_lv":["1","1","1","1","1"],"m_pcommand_lv":["1","1","1"],"m_acommand_id":["600610","600611","600612","0","0"],"m_pcommand_id":["113","114","0"],"drops":[],"move":"2"}],"background_id":2201,"background_effect_id":0,"background_color":"7F7F7F","meta_area":"x=0&y=1&id=7001010#x=0&y=3&id=7001010#x=1&y=2&id=7001010#x=2&y=0&id=7001010#x=2&y=4&id=7001010"}],"drop_eq":{"id":"10816"},"retry":0,"move_count":0,"dead_count":0,"consumed":0}}],"extra":{"t_member_items":[{"item_id":"9101","item_type":"91","item_num":"7"},{"item_id":"9102","item_type":"91
193
","item_num":"9"},{"item_id":"9103","item_type":"91","item_num":"6"},{"item_id":"9104","item_type":"91","item_num":"6"},{"item_id":"9105","item_type":"91","item_num":"7"},{"item_id":"9106","item_type":"91","item_num":"6"},{"item_id":"9107","item_type":"91","item_num":"6"},{"item_id":"9108","item_type":"91","item_num":"6"},{"item_id":"9109","item_type":"91","item_num":"7"}]}},"timestamp":"1523081349"}